tzf.pyramid_yml-2.0.0-py3.7-nspkg.pth
tests/__init__.py
tests/conftest.py
tests/test_basic.py
tests/test_defaults.py
tests/test_multifile.py
tests/test_prodenv.py
tests/test_script.py
tzf/pyramid_yml/__init__.py
tzf/pyramid_yml/scripts.py
tzf.pyramid_yml-2.0.0.dist-info/AUTHORS.rst
tzf.pyramid_yml-2.0.0.dist-info/LICENSE
tzf.pyramid_yml-2.0.0.dist-info/METADATA
tzf.pyramid_yml-2.0.0.dist-info/WHEEL
tzf.pyramid_yml-2.0.0.dist-info/entry_points.txt
tzf.pyramid_yml-2.0.0.dist-info/namespace_packages.txt
tzf.pyramid_yml-2.0.0.dist-info/top_level.txt
tzf.pyramid_yml-2.0.0.dist-info/RECORD
