Metadata-Version: 2.1
Name: tzf.pyramid-yml
Version: 2.0.0
Summary: Loads a yml defined configuration
Home-page: https://github.com/fizyk/pyramid_yml
Author: Grzegorz Sliwinski
Author-email: fizyk@fizyk.net.pl
License: MIT License
Keywords: pyramid yml configuration
Platform: UNKNOWN
Classifier: Development Status :: 5 - Production/Stable
Classifier: Environment :: Web Environment
Classifier: Intended Audience :: Developers
Classifier: License :: OSI Approved :: MIT License
Classifier: Natural Language :: English
Classifier: Operating System :: OS Independent
Classifier: Programming Language :: Python
Classifier: Programming Language :: Python :: 3
Classifier: Programming Language :: Python :: 3.5
Classifier: Programming Language :: Python :: 3.6
Classifier: Programming Language :: Python :: 3.7
Classifier: Framework :: Pyramid
Classifier: Topic :: Internet :: WWW/HTTP
Classifier: Topic :: Internet :: WWW/HTTP :: WSGI
Classifier: Topic :: Software Development :: Libraries :: Python Modules
Requires-Python: >=3.5
Requires-Dist: pyramid
Requires-Dist: pymlconf (!=0.5.0,<1.0.0,>=0.3.7)
Provides-Extra: docs
Requires-Dist: sphinx ; extra == 'docs'
Provides-Extra: tests
Requires-Dist: pytest (>=3.3.0) ; extra == 'tests'
Requires-Dist: pytest-cov (>=2.6.0) ; extra == 'tests'
Requires-Dist: pytest-pyramid (>=0.3.0) ; extra == 'tests'
